pyinstance/__init__.py
pyinstance-1.0.dist-info/DESCRIPTION.rst
pyinstance-1.0.dist-info/METADATA
pyinstance-1.0.dist-info/RECORD
pyinstance-1.0.dist-info/WHEEL
pyinstance-1.0.dist-info/metadata.json
pyinstance-1.0.dist-info/top_level.txt
pyinstance-1.0.dist-info/zip-safe
