Metadata-Version: 2.0
Name: pyinstance
Version: 1.0
Summary: Python Object Instance Management
Home-page: https://github.com/TestInABox/pyinstance
Author: Benjamen R. Meyer
Author-email: bm_witness@yahoo.com
License: Apache License 2.0
Platform: UNKNOWN
Classifier: Intended Audience :: Developers
Classifier: License :: OSI Approved :: MIT License
Classifier: Topic :: Software Development :: Testing
